{
  "selectResult": [{
    "len": 10000,
    "time": 32
  }, {
    "len": 10000,
    "time": 46
  }, {
    "len": 10000,
    "time": 30
  }, {
    "len": 10000,
    "time": 29
  }, {
    "len": 10000,
    "time": 30
  }, {
    "len": 10000,
    "time": 29
  }, {
    "len": 10000,
    "time": 30
  }, {
    "len": 10000,
    "time": 30
  }, {
    "len": 10000,
    "time": 30
  }, {
    "len": 10000,
    "time": 29
  }, {
    "len": 10000,
    "time": 30
  }, {
    "len": 10000,
    "time": 30
  }, {
    "len": 10000,
    "time": 29
  }, {
    "len": 10000,
    "time": 29
  }, {
    "len": 10000,
    "time": 29
  }, {
    "len": 10000,
    "time": 29
  }, {
    "len": 10000,
    "time": 30
  }, {
    "len": 10000,
    "time": 30
  }, {
    "len": 10000,
    "time": 29
  }, {
    "len": 10000,
    "time": 30
  }, {
    "len": 20000,
    "time": 115
  }, {
    "len": 20000,
    "time": 116
  }, {
    "len": 20000,
    "time": 112
  }, {
    "len": 20000,
    "time": 111
  }, {
    "len": 20000,
    "time": 114
  }, {
    "len": 20000,
    "time": 111
  }, {
    "len": 20000,
    "time": 114
  }, {
    "len": 20000,
    "time": 112
  }, {
    "len": 20000,
    "time": 112
  }, {
    "len": 20000,
    "time": 114
  }, {
    "len": 20000,
    "time": 112
  }, {
    "len": 20000,
    "time": 116
  }, {
    "len": 20000,
    "time": 113
  }, {
    "len": 20000,
    "time": 114
  }, {
    "len": 20000,
    "time": 111
  }, {
    "len": 20000,
    "time": 110
  }, {
    "len": 20000,
    "time": 115
  }, {
    "len": 20000,
    "time": 112
  }, {
    "len": 20000,
    "time": 112
  }, {
    "len": 20000,
    "time": 121
  }, {
    "len": 30000,
    "time": 252
  }, {
    "len": 30000,
    "time": 256
  }, {
    "len": 30000,
    "time": 257
  }, {
    "len": 30000,
    "time": 256
  }, {
    "len": 30000,
    "time": 245
  }, {
    "len": 30000,
    "time": 254
  }, {
    "len": 30000,
    "time": 250
  }, {
    "len": 30000,
    "time": 250
  }, {
    "len": 30000,
    "time": 251
  }, {
    "len": 30000,
    "time": 253
  }, {
    "len": 30000,
    "time": 255
  }, {
    "len": 30000,
    "time": 249
  }, {
    "len": 30000,
    "time": 251
  }, {
    "len": 30000,
    "time": 250
  }, {
    "len": 30000,
    "time": 251
  }, {
    "len": 30000,
    "time": 250
  }, {
    "len": 30000,
    "time": 249
  }, {
    "len": 30000,
    "time": 251
  }, {
    "len": 30000,
    "time": 260
  }, {
    "len": 30000,
    "time": 253
  }, {
    "len": 40000,
    "time": 441
  }, {
    "len": 40000,
    "time": 443
  }, {
    "len": 40000,
    "time": 450
  }, {
    "len": 40000,
    "time": 445
  }, {
    "len": 40000,
    "time": 445
  }, {
    "len": 40000,
    "time": 456
  }, {
    "len": 40000,
    "time": 449
  }, {
    "len": 40000,
    "time": 446
  }, {
    "len": 40000,
    "time": 451
  }, {
    "len": 40000,
    "time": 448
  }, {
    "len": 40000,
    "time": 446
  }, {
    "len": 40000,
    "time": 448
  }, {
    "len": 40000,
    "time": 446
  }, {
    "len": 40000,
    "time": 454
  }, {
    "len": 40000,
    "time": 450
  }, {
    "len": 40000,
    "time": 442
  }, {
    "len": 40000,
    "time": 454
  }, {
    "len": 40000,
    "time": 444
  }, {
    "len": 40000,
    "time": 448
  }, {
    "len": 40000,
    "time": 443
  }, {
    "len": 50000,
    "time": 701
  }, {
    "len": 50000,
    "time": 696
  }, {
    "len": 50000,
    "time": 697
  }, {
    "len": 50000,
    "time": 698
  }, {
    "len": 50000,
    "time": 706
  }, {
    "len": 50000,
    "time": 691
  }, {
    "len": 50000,
    "time": 702
  }, {
    "len": 50000,
    "time": 697
  }, {
    "len": 50000,
    "time": 696
  }, {
    "len": 50000,
    "time": 703
  }, {
    "len": 50000,
    "time": 698
  }, {
    "len": 50000,
    "time": 701
  }, {
    "len": 50000,
    "time": 698
  }, {
    "len": 50000,
    "time": 702
  }, {
    "len": 50000,
    "time": 697
  }, {
    "len": 50000,
    "time": 703
  }, {
    "len": 50000,
    "time": 696
  }, {
    "len": 50000,
    "time": 702
  }, {
    "len": 50000,
    "time": 708
  }, {
    "len": 50000,
    "time": 695
  }],
  "insertResult": [{
    "len": 10000,
    "time": 38
  }, {
    "len": 10000,
    "time": 38
  }, {
    "len": 10000,
    "time": 36
  }, {
    "len": 10000,
    "time": 36
  }, {
    "len": 10000,
    "time": 37
  }, {
    "len": 10000,
    "time": 37
  }, {
    "len": 10000,
    "time": 36
  }, {
    "len": 10000,
    "time": 37
  }, {
    "len": 10000,
    "time": 37
  }, {
    "len": 10000,
    "time": 37
  }, {
    "len": 10000,
    "time": 38
  }, {
    "len": 10000,
    "time": 37
  }, {
    "len": 10000,
    "time": 36
  }, {
    "len": 10000,
    "time": 36
  }, {
    "len": 10000,
    "time": 36
  }, {
    "len": 10000,
    "time": 35
  }, {
    "len": 10000,
    "time": 38
  }, {
    "len": 10000,
    "time": 37
  }, {
    "len": 10000,
    "time": 35
  }, {
    "len": 10000,
    "time": 35
  }, {
    "len": 20000,
    "time": 152
  }, {
    "len": 20000,
    "time": 149
  }, {
    "len": 20000,
    "time": 571
  }, {
    "len": 20000,
    "time": 191
  }, {
    "len": 20000,
    "time": 145
  }, {
    "len": 20000,
    "time": 146
  }, {
    "len": 20000,
    "time": 276
  }, {
    "len": 20000,
    "time": 148
  }, {
    "len": 20000,
    "time": 142
  }, {
    "len": 20000,
    "time": 346
  }, {
    "len": 20000,
    "time": 144
  }, {
    "len": 20000,
    "time": 146
  }, {
    "len": 20000,
    "time": 461
  }, {
    "len": 20000,
    "time": 156
  }, {
    "len": 20000,
    "time": 146
  }, {
    "len": 20000,
    "time": 564
  }, {
    "len": 20000,
    "time": 189
  }, {
    "len": 20000,
    "time": 148
  }, {
    "len": 20000,
    "time": 146
  }, {
    "len": 20000,
    "time": 145
  }, {
    "len": 30000,
    "time": 423
  }, {
    "len": 30000,
    "time": 322
  }, {
    "len": 30000,
    "time": 321
  }, {
    "len": 30000,
    "time": 322
  }, {
    "len": 30000,
    "time": 322
  }, {
    "len": 30000,
    "time": 323
  }, {
    "len": 30000,
    "time": 325
  }, {
    "len": 30000,
    "time": 326
  }, {
    "len": 30000,
    "time": 329
  }, {
    "len": 30000,
    "time": 1161
  }, {
    "len": 30000,
    "time": 326
  }, {
    "len": 30000,
    "time": 903
  }, {
    "len": 30000,
    "time": 330
  }, {
    "len": 30000,
    "time": 673
  }, {
    "len": 30000,
    "time": 350
  }, {
    "len": 30000,
    "time": 435
  }, {
    "len": 30000,
    "time": 328
  }, {
    "len": 30000,
    "time": 326
  }, {
    "len": 30000,
    "time": 326
  }, {
    "len": 30000,
    "time": 325
  }, {
    "len": 40000,
    "time": 589
  }, {
    "len": 40000,
    "time": 888
  }, {
    "len": 40000,
    "time": 596
  }, {
    "len": 40000,
    "time": 1709
  }, {
    "len": 40000,
    "time": 594
  }, {
    "len": 40000,
    "time": 588
  }, {
    "len": 40000,
    "time": 836
  }, {
    "len": 40000,
    "time": 605
  }, {
    "len": 40000,
    "time": 1613
  }, {
    "len": 40000,
    "time": 587
  }, {
    "len": 40000,
    "time": 593
  }, {
    "len": 40000,
    "time": 749
  }, {
    "len": 40000,
    "time": 595
  }, {
    "len": 40000,
    "time": 601
  }, {
    "len": 40000,
    "time": 585
  }, {
    "len": 40000,
    "time": 604
  }, {
    "len": 40000,
    "time": 595
  }, {
    "len": 40000,
    "time": 595
  }, {
    "len": 40000,
    "time": 1313
  }, {
    "len": 40000,
    "time": 589
  }, {
    "len": 50000,
    "time": 955
  }, {
    "len": 50000,
    "time": 1933
  }, {
    "len": 50000,
    "time": 953
  }, {
    "len": 50000,
    "time": 963
  }, {
    "len": 50000,
    "time": 2977
  }, {
    "len": 50000,
    "time": 981
  }, {
    "len": 50000,
    "time": 1005
  }, {
    "len": 50000,
    "time": 949
  }, {
    "len": 50000,
    "time": 950
  }, {
    "len": 50000,
    "time": 976
  }, {
    "len": 50000,
    "time": 955
  }, {
    "len": 50000,
    "time": 953
  }, {
    "len": 50000,
    "time": 1470
  }, {
    "len": 50000,
    "time": 941
  }, {
    "len": 50000,
    "time": 945
  }, {
    "len": 50000,
    "time": 2287
  }, {
    "len": 50000,
    "time": 957
  }, {
    "len": 50000,
    "time": 963
  }, {
    "len": 50000,
    "time": 3377
  }, {
    "len": 50000,
    "time": 951
  }],
  "mergeResult": [{
    "len": 10000,
    "time": 6
  }, {
    "len": 10000,
    "time": 1
  }, {
    "len": 10000,
    "time": 1
  }, {
    "len": 10000,
    "time": 1
  }, {
    "len": 10000,
    "time": 1
  }, {
    "len": 10000,
    "time": 2
  }, {
    "len": 10000,
    "time": 1
  }, {
    "len": 10000,
    "time": 1
  }, {
    "len": 10000,
    "time": 1
  }, {
    "len": 10000,
    "time": 1
  }, {
    "len": 10000,
    "time": 1
  }, {
    "len": 10000,
    "time": 1
  }, {
    "len": 10000,
    "time": 1
  }, {
    "len": 10000,
    "time": 1
  }, {
    "len": 10000,
    "time": 1
  }, {
    "len": 10000,
    "time": 1
  }, {
    "len": 10000,
    "time": 1
  }, {
    "len": 10000,
    "time": 1
  }, {
    "len": 10000,
    "time": 1
  }, {
    "len": 10000,
    "time": 1
  }, {
    "len": 20000,
    "time": 2
  }, {
    "len": 20000,
    "time": 2
  }, {
    "len": 20000,
    "time": 4
  }, {
    "len": 20000,
    "time": 2
  }, {
    "len": 20000,
    "time": 2
  }, {
    "len": 20000,
    "time": 3
  }, {
    "len": 20000,
    "time": 2
  }, {
    "len": 20000,
    "time": 3
  }, {
    "len": 20000,
    "time": 2
  }, {
    "len": 20000,
    "time": 2
  }, {
    "len": 20000,
    "time": 3
  }, {
    "len": 20000,
    "time": 2
  }, {
    "len": 20000,
    "time": 2
  }, {
    "len": 20000,
    "time": 2
  }, {
    "len": 20000,
    "time": 3
  }, {
    "len": 20000,
    "time": 3
  }, {
    "len": 20000,
    "time": 2
  }, {
    "len": 20000,
    "time": 3
  }, {
    "len": 20000,
    "time": 2
  }, {
    "len": 20000,
    "time": 3
  }, {
    "len": 30000,
    "time": 4
  }, {
    "len": 30000,
    "time": 4
  }, {
    "len": 30000,
    "time": 4
  }, {
    "len": 30000,
    "time": 4
  }, {
    "len": 30000,
    "time": 4
  }, {
    "len": 30000,
    "time": 3
  }, {
    "len": 30000,
    "time": 4
  }, {
    "len": 30000,
    "time": 3
  }, {
    "len": 30000,
    "time": 4
  }, {
    "len": 30000,
    "time": 4
  }, {
    "len": 30000,
    "time": 3
  }, {
    "len": 30000,
    "time": 4
  }, {
    "len": 30000,
    "time": 4
  }, {
    "len": 30000,
    "time": 3
  }, {
    "len": 30000,
    "time": 3
  }, {
    "len": 30000,
    "time": 4
  }, {
    "len": 30000,
    "time": 4
  }, {
    "len": 30000,
    "time": 5
  }, {
    "len": 30000,
    "time": 4
  }, {
    "len": 30000,
    "time": 4
  }, {
    "len": 40000,
    "time": 7
  }, {
    "len": 40000,
    "time": 6
  }, {
    "len": 40000,
    "time": 5
  }, {
    "len": 40000,
    "time": 6
  }, {
    "len": 40000,
    "time": 5
  }, {
    "len": 40000,
    "time": 5
  }, {
    "len": 40000,
    "time": 5
  }, {
    "len": 40000,
    "time": 6
  }, {
    "len": 40000,
    "time": 6
  }, {
    "len": 40000,
    "time": 5
  }, {
    "len": 40000,
    "time": 5
  }, {
    "len": 40000,
    "time": 5
  }, {
    "len": 40000,
    "time": 5
  }, {
    "len": 40000,
    "time": 5
  }, {
    "len": 40000,
    "time": 5
  }, {
    "len": 40000,
    "time": 5
  }, {
    "len": 40000,
    "time": 5
  }, {
    "len": 40000,
    "time": 5
  }, {
    "len": 40000,
    "time": 5
  }, {
    "len": 40000,
    "time": 5
  }, {
    "len": 50000,
    "time": 7
  }, {
    "len": 50000,
    "time": 7
  }, {
    "len": 50000,
    "time": 7
  }, {
    "len": 50000,
    "time": 6
  }, {
    "len": 50000,
    "time": 6
  }, {
    "len": 50000,
    "time": 6
  }, {
    "len": 50000,
    "time": 8
  }, {
    "len": 50000,
    "time": 6
  }, {
    "len": 50000,
    "time": 6
  }, {
    "len": 50000,
    "time": 7
  }, {
    "len": 50000,
    "time": 7
  }, {
    "len": 50000,
    "time": 7
  }, {
    "len": 50000,
    "time": 6
  }, {
    "len": 50000,
    "time": 7
  }, {
    "len": 50000,
    "time": 6
  }, {
    "len": 50000,
    "time": 7
  }, {
    "len": 50000,
    "time": 7
  }, {
    "len": 50000,
    "time": 7
  }, {
    "len": 50000,
    "time": 7
  }, {
    "len": 50000,
    "time": 7
  }],
  "bubbleResult": [{
    "len": 10000,
    "time": 45
  }, {
    "len": 10000,
    "time": 43
  }, {
    "len": 10000,
    "time": 44
  }, {
    "len": 10000,
    "time": 44
  }, {
    "len": 10000,
    "time": 41
  }, {
    "len": 10000,
    "time": 42
  }, {
    "len": 10000,
    "time": 41
  }, {
    "len": 10000,
    "time": 47
  }, {
    "len": 10000,
    "time": 43
  }, {
    "len": 10000,
    "time": 42
  }, {
    "len": 10000,
    "time": 41
  }, {
    "len": 10000,
    "time": 46
  }, {
    "len": 10000,
    "time": 42
  }, {
    "len": 10000,
    "time": 41
  }, {
    "len": 10000,
    "time": 42
  }, {
    "len": 10000,
    "time": 41
  }, {
    "len": 10000,
    "time": 41
  }, {
    "len": 10000,
    "time": 41
  }, {
    "len": 10000,
    "time": 42
  }, {
    "len": 10000,
    "time": 40
  }, {
    "len": 20000,
    "time": 163
  }, {
    "len": 20000,
    "time": 160
  }, {
    "len": 20000,
    "time": 165
  }, {
    "len": 20000,
    "time": 161
  }, {
    "len": 20000,
    "time": 158
  }, {
    "len": 20000,
    "time": 159
  }, {
    "len": 20000,
    "time": 170
  }, {
    "len": 20000,
    "time": 159
  }, {
    "len": 20000,
    "time": 160
  }, {
    "len": 20000,
    "time": 161
  }, {
    "len": 20000,
    "time": 159
  }, {
    "len": 20000,
    "time": 160
  }, {
    "len": 20000,
    "time": 172
  }, {
    "len": 20000,
    "time": 162
  }, {
    "len": 20000,
    "time": 160
  }, {
    "len": 20000,
    "time": 160
  }, {
    "len": 20000,
    "time": 159
  }, {
    "len": 20000,
    "time": 157
  }, {
    "len": 20000,
    "time": 159
  }, {
    "len": 20000,
    "time": 162
  }, {
    "len": 30000,
    "time": 356
  }, {
    "len": 30000,
    "time": 350
  }, {
    "len": 30000,
    "time": 356
  }, {
    "len": 30000,
    "time": 356
  }, {
    "len": 30000,
    "time": 354
  }, {
    "len": 30000,
    "time": 357
  }, {
    "len": 30000,
    "time": 354
  }, {
    "len": 30000,
    "time": 353
  }, {
    "len": 30000,
    "time": 355
  }, {
    "len": 30000,
    "time": 351
  }, {
    "len": 30000,
    "time": 359
  }, {
    "len": 30000,
    "time": 359
  }, {
    "len": 30000,
    "time": 351
  }, {
    "len": 30000,
    "time": 356
  }, {
    "len": 30000,
    "time": 356
  }, {
    "len": 30000,
    "time": 353
  }, {
    "len": 30000,
    "time": 350
  }, {
    "len": 30000,
    "time": 349
  }, {
    "len": 30000,
    "time": 351
  }, {
    "len": 30000,
    "time": 351
  }, {
    "len": 40000,
    "time": 617
  }, {
    "len": 40000,
    "time": 631
  }, {
    "len": 40000,
    "time": 623
  }, {
    "len": 40000,
    "time": 613
  }, {
    "len": 40000,
    "time": 623
  }, {
    "len": 40000,
    "time": 624
  }, {
    "len": 40000,
    "time": 615
  }, {
    "len": 40000,
    "time": 615
  }, {
    "len": 40000,
    "time": 631
  }, {
    "len": 40000,
    "time": 616
  }, {
    "len": 40000,
    "time": 621
  }, {
    "len": 40000,
    "time": 630
  }, {
    "len": 40000,
    "time": 622
  }, {
    "len": 40000,
    "time": 622
  }, {
    "len": 40000,
    "time": 619
  }, {
    "len": 40000,
    "time": 629
  }, {
    "len": 40000,
    "time": 634
  }, {
    "len": 40000,
    "time": 620
  }, {
    "len": 40000,
    "time": 614
  }, {
    "len": 40000,
    "time": 625
  }, {
    "len": 50000,
    "time": 972
  }, {
    "len": 50000,
    "time": 977
  }, {
    "len": 50000,
    "time": 979
  }, {
    "len": 50000,
    "time": 969
  }, {
    "len": 50000,
    "time": 975
  }, {
    "len": 50000,
    "time": 982
  }, {
    "len": 50000,
    "time": 987
  }, {
    "len": 50000,
    "time": 964
  }, {
    "len": 50000,
    "time": 963
  }, {
    "len": 50000,
    "time": 978
  }, {
    "len": 50000,
    "time": 963
  }, {
    "len": 50000,
    "time": 966
  }, {
    "len": 50000,
    "time": 970
  }, {
    "len": 50000,
    "time": 971
  }, {
    "len": 50000,
    "time": 959
  }, {
    "len": 50000,
    "time": 963
  }, {
    "len": 50000,
    "time": 982
  }, {
    "len": 50000,
    "time": 977
  }, {
    "len": 50000,
    "time": 970
  }, {
    "len": 50000,
    "time": 964
  }],
  "quickResult": [{
    "len": 10000,
    "time": 6
  }, {
    "len": 10000,
    "time": 1
  }, {
    "len": 10000,
    "time": 1
  }, {
    "len": 10000,
    "time": 1
  }, {
    "len": 10000,
    "time": 0
  }, {
    "len": 10000,
    "time": 0
  }, {
    "len": 10000,
    "time": 1
  }, {
    "len": 10000,
    "time": 1
  }, {
    "len": 10000,
    "time": 1
  }, {
    "len": 10000,
    "time": 1
  }, {
    "len": 10000,
    "time": 0
  }, {
    "len": 10000,
    "time": 0
  }, {
    "len": 10000,
    "time": 1
  }, {
    "len": 10000,
    "time": 0
  }, {
    "len": 10000,
    "time": 1
  }, {
    "len": 10000,
    "time": 0
  }, {
    "len": 10000,
    "time": 0
  }, {
    "len": 10000,
    "time": 0
  }, {
    "len": 10000,
    "time": 1
  }, {
    "len": 10000,
    "time": 1
  }, {
    "len": 20000,
    "time": 1
  }, {
    "len": 20000,
    "time": 2
  }, {
    "len": 20000,
    "time": 1
  }, {
    "len": 20000,
    "time": 2
  }, {
    "len": 20000,
    "time": 1
  }, {
    "len": 20000,
    "time": 1
  }, {
    "len": 20000,
    "time": 2
  }, {
    "len": 20000,
    "time": 1
  }, {
    "len": 20000,
    "time": 1
  }, {
    "len": 20000,
    "time": 2
  }, {
    "len": 20000,
    "time": 1
  }, {
    "len": 20000,
    "time": 1
  }, {
    "len": 20000,
    "time": 1
  }, {
    "len": 20000,
    "time": 1
  }, {
    "len": 20000,
    "time": 1
  }, {
    "len": 20000,
    "time": 1
  }, {
    "len": 20000,
    "time": 2
  }, {
    "len": 20000,
    "time": 1
  }, {
    "len": 20000,
    "time": 1
  }, {
    "len": 20000,
    "time": 1
  }, {
    "len": 30000,
    "time": 2
  }, {
    "len": 30000,
    "time": 2
  }, {
    "len": 30000,
    "time": 2
  }, {
    "len": 30000,
    "time": 2
  }, {
    "len": 30000,
    "time": 2
  }, {
    "len": 30000,
    "time": 1
  }, {
    "len": 30000,
    "time": 2
  }, {
    "len": 30000,
    "time": 2
  }, {
    "len": 30000,
    "time": 2
  }, {
    "len": 30000,
    "time": 2
  }, {
    "len": 30000,
    "time": 3
  }, {
    "len": 30000,
    "time": 2
  }, {
    "len": 30000,
    "time": 2
  }, {
    "len": 30000,
    "time": 2
  }, {
    "len": 30000,
    "time": 2
  }, {
    "len": 30000,
    "time": 2
  }, {
    "len": 30000,
    "time": 2
  }, {
    "len": 30000,
    "time": 2
  }, {
    "len": 30000,
    "time": 2
  }, {
    "len": 30000,
    "time": 2
  }, {
    "len": 40000,
    "time": 2
  }, {
    "len": 40000,
    "time": 3
  }, {
    "len": 40000,
    "time": 3
  }, {
    "len": 40000,
    "time": 2
  }, {
    "len": 40000,
    "time": 3
  }, {
    "len": 40000,
    "time": 3
  }, {
    "len": 40000,
    "time": 3
  }, {
    "len": 40000,
    "time": 3
  }, {
    "len": 40000,
    "time": 3
  }, {
    "len": 40000,
    "time": 3
  }, {
    "len": 40000,
    "time": 3
  }, {
    "len": 40000,
    "time": 3
  }, {
    "len": 40000,
    "time": 3
  }, {
    "len": 40000,
    "time": 3
  }, {
    "len": 40000,
    "time": 3
  }, {
    "len": 40000,
    "time": 2
  }, {
    "len": 40000,
    "time": 3
  }, {
    "len": 40000,
    "time": 2
  }, {
    "len": 40000,
    "time": 3
  }, {
    "len": 40000,
    "time": 3
  }, {
    "len": 50000,
    "time": 3
  }, {
    "len": 50000,
    "time": 4
  }, {
    "len": 50000,
    "time": 3
  }, {
    "len": 50000,
    "time": 4
  }, {
    "len": 50000,
    "time": 3
  }, {
    "len": 50000,
    "time": 3
  }, {
    "len": 50000,
    "time": 3
  }, {
    "len": 50000,
    "time": 4
  }, {
    "len": 50000,
    "time": 4
  }, {
    "len": 50000,
    "time": 3
  }, {
    "len": 50000,
    "time": 3
  }, {
    "len": 50000,
    "time": 3
  }, {
    "len": 50000,
    "time": 4
  }, {
    "len": 50000,
    "time": 3
  }, {
    "len": 50000,
    "time": 5
  }, {
    "len": 50000,
    "time": 3
  }, {
    "len": 50000,
    "time": 4
  }, {
    "len": 50000,
    "time": 3
  }, {
    "len": 50000,
    "time": 3
  }, {
    "len": 50000,
    "time": 4
  }]
}